wallace/half_adder.v
module half_adder(
    Data_in_A,
    Data_in_B,
    Data_out_Sum,
    Data_out_Carry
    );

 
    input Data_in_A;
    input Data_in_B;

    output Data_out_Sum;
     output Data_out_Carry;
     
    
     assign Data_out_Sum = Data_in_A ^ Data_in_B;  //XOR operation
     assign Data_out_Carry = Data_in_A & Data_in_B; //AND operation
    
endmodule

wallace/full_adder.v
`include "half_adder.v"
module full_adder(
    Data_in_A,  //input A
    Data_in_B,  //input B
    Data_in_C,  //input C
     Data_out_Sum,
     Data_out_Carry
    );

    input Data_in_A;
    input Data_in_B;
     input Data_in_C;
    

    output Data_out_Sum;
     output Data_out_Carry;
     //Internal variables
     wire ha1_sum;
     wire ha2_sum;
     wire ha1_carry;
     wire ha2_carry;
     wire Data_out_Sum;
     wire Data_out_Carry;

    //half adder 1
    half_adder ha1(
        .Data_in_A(Data_in_A),
        .Data_in_B(Data_in_B),
        .Data_out_Sum(ha1_sum),
        .Data_out_Carry(ha1_carry)
    );
    
    //half adder 2
    half_adder ha2(
        .Data_in_A(Data_in_C),
        .Data_in_B(ha1_sum),
        .Data_out_Sum(ha2_sum),
        .Data_out_Carry(ha2_carry)
    );

    
    assign Data_out_Sum = ha2_sum;  
    
    assign Data_out_Carry = ha1_carry | ha2_carry;
    
endmodule

wallace/wallace.v

`include "full_adder.v"

module wallace(A,B,prod);
    
    //inputs and outputs
    input [3:0] A,B;
    output [7:0] prod;
    //internal variables.
    wire s11,s12,s13,s14,s15,s22,s23,s24,s25,s26,s32,s33,s34,s35,s36,s37;
    wire c11,c12,c13,c14,c15,c22,c23,c24,c25,c26,c32,c33,c34,c35,c36,c37;
    wire [6:0] p0,p1,p2,p3;

//initialize the p's.
    assign  p0 = A & {4{B[0]}};
    assign  p1 = A & {4{B[1]}};
    assign  p2 = A & {4{B[2]}};
    assign  p3 = A & {4{B[3]}};

 
    assign prod[0] = p0[0];
    assign prod[1] = s11;
    assign prod[2] = s22;
    assign prod[3] = s32;
    assign prod[4] = s34;
    assign prod[5] = s35;
    assign prod[6] = s36;
    assign prod[7] = s37;

//first stage
    half_adder ha11 (p0[1],p1[0],s11,c11);
    full_adder fa12(p0[2],p1[1],p2[0],s12,c12);
    full_adder fa13(p0[3],p1[2],p2[1],s13,c13);
    full_adder fa14(p1[3],p2[2],p3[1],s14,c14);
    half_adder ha15(p2[3],p3[2],s15,c15);

//second stage
    half_adder ha22 (c11,s12,s22,c22);
    full_adder fa23 (p3[0],c12,s13,s23,c23);
    full_adder fa24 (c13,c32,s14,s24,c24);
    full_adder fa25 (c14,c24,s15,s25,c25);
    full_adder fa26 (c15,c25,p3[3],s26,c26);

//third stage
    half_adder ha32(c22,s23,s32,c32);
    half_adder ha34(c23,s24,s34,c34);
    half_adder ha35(c34,s25,s35,c35);
    half_adder ha36(c35,s26,s36,c36);
    half_adder ha37(c36,c26,s37,c37);

endmodule

wallace/wallace_tb.v
`include "wallace.v"
module tb;

    // Inputs
    reg [3:0] A;
    reg [3:0] B;

    // Outputs
    wire [7:0] prod;
    integer i,j,error;

    
    wallace uut (
        .A(A), 
        .B(B), 
        .prod(prod)
    );

    initial begin
        $dumpfile("wallace_tb.vcd"); 
        $dumpvars(0, tb);  
        // Apply inputs for the whole range of A and B.
        // 16*16 = 256 inputs.
        error = 0;
        for(i=0;i <=15;i = i+1)
            for(j=0;j <=15;j = j+1) 
            begin
                A <= i; 
                B <= j;
                #1;
                if(prod != A*B) //if the result isnt correct increment "error".
                    error = error + 1;  
            end     
    end
      
endmodule

wallace/wallace_tb.vcd
$date
	Mon Apr 28 12:00:22 2025
$end
$version
	Icarus Verilog
$end
$timescale
	1s
$end
$scope module tb $end
$var wire 8 ! prod [7:0] $end
$var reg 4 " A [3:0] $end
$var reg 4 # B [3:0] $end
$var integer 32 $ error [31:0] $end
$var integer 32 % i [31:0] $end
$var integer 32 & j [31:0] $end
$scope module uut $end
$var wire 4 ' A [3:0] $end
$var wire 4 ( B [3:0] $end
$var wire 7 ) p0 [6:0] $end
$var wire 7 * p1 [6:0] $end
$var wire 7 + p2 [6:0] $end
$var wire 7 , p3 [6:0] $end
$var wire 1 - s37 $end
$var wire 1 . s36 $end
$var wire 1 / s35 $end
$var wire 1 0 s34 $end
$var wire 1 1 s32 $end
$var wire 1 2 s26 $end
$var wire 1 3 s25 $end
$var wire 1 4 s24 $end
$var wire 1 5 s23 $end
$var wire 1 6 s22 $end
$var wire 1 7 s15 $end
$var wire 1 8 s14 $end
$var wire 1 9 s13 $end
$var wire 1 : s12 $end
$var wire 1 ; s11 $end
$var wire 8 < prod [7:0] $end
$var wire 1 = c37 $end
$var wire 1 > c36 $end
$var wire 1 ? c35 $end
$var wire 1 @ c34 $end
$var wire 1 A c32 $end
$var wire 1 B c26 $end
$var wire 1 C c25 $end
$var wire 1 D c24 $end
$var wire 1 E c23 $end
$var wire 1 F c22 $end
$var wire 1 G c15 $end
$var wire 1 H c14 $end
$var wire 1 I c13 $end
$var wire 1 J c12 $end
$var wire 1 K c11 $end
$scope module fa12 $end
$var wire 1 L Data_in_A $end
$var wire 1 M Data_in_B $end
$var wire 1 N Data_in_C $end
$var wire 1 J Data_out_Carry $end
$var wire 1 : Data_out_Sum $end
$var wire 1 O ha2_sum $end
$var wire 1 P ha2_carry $end
$var wire 1 Q ha1_sum $end
$var wire 1 R ha1_carry $end
$scope module ha1 $end
$var wire 1 L Data_in_A $end
$var wire 1 M Data_in_B $end
$var wire 1 R Data_out_Carry $end
$var wire 1 Q Data_out_Sum $end
$upscope $end
$scope module ha2 $end
$var wire 1 N Data_in_A $end
$var wire 1 Q Data_in_B $end
$var wire 1 P Data_out_Carry $end
$var wire 1 O Data_out_Sum $end
$upscope $end
$upscope $end
$scope module fa13 $end
$var wire 1 S Data_in_A $end
$var wire 1 T Data_in_B $end
$var wire 1 U Data_in_C $end
$var wire 1 I Data_out_Carry $end
$var wire 1 9 Data_out_Sum $end
$var wire 1 V ha2_sum $end
$var wire 1 W ha2_carry $end
$var wire 1 X ha1_sum $end
$var wire 1 Y ha1_carry $end
$scope module ha1 $end
$var wire 1 S Data_in_A $end
$var wire 1 T Data_in_B $end
$var wire 1 Y Data_out_Carry $end
$var wire 1 X Data_out_Sum $end
$upscope $end
$scope module ha2 $end
$var wire 1 U Data_in_A $end
$var wire 1 X Data_in_B $end
$var wire 1 W Data_out_Carry $end
$var wire 1 V Data_out_Sum $end
$upscope $end
$upscope $end
$scope module fa14 $end
$var wire 1 Z Data_in_A $end
$var wire 1 [ Data_in_B $end
$var wire 1 \ Data_in_C $end
$var wire 1 H Data_out_Carry $end
$var wire 1 8 Data_out_Sum $end
$var wire 1 ] ha2_sum $end
$var wire 1 ^ ha2_carry $end
$var wire 1 _ ha1_sum $end
$var wire 1 ` ha1_carry $end
$scope module ha1 $end
$var wire 1 Z Data_in_A $end
$var wire 1 [ Data_in_B $end
$var wire 1 ` Data_out_Carry $end
$var wire 1 _ Data_out_Sum $end
$upscope $end
$scope module ha2 $end
$var wire 1 \ Data_in_A $end
$var wire 1 _ Data_in_B $end
$var wire 1 ^ Data_out_Carry $end
$var wire 1 ] Data_out_Sum $end
$upscope $end
$upscope $end
$scope module fa23 $end
$var wire 1 a Data_in_A $end
$var wire 1 J Data_in_B $end
$var wire 1 9 Data_in_C $end
$var wire 1 E Data_out_Carry $end
$var wire 1 5 Data_out_Sum $end
$var wire 1 b ha2_sum $end
$var wire 1 c ha2_carry $end
$var wire 1 d ha1_sum $end
$var wire 1 e ha1_carry $end
$scope module ha1 $end
$var wire 1 a Data_in_A $end
$var wire 1 J Data_in_B $end
$var wire 1 e Data_out_Carry $end
$var wire 1 d Data_out_Sum $end
$upscope $end
$scope module ha2 $end
$var wire 1 9 Data_in_A $end
$var wire 1 d Data_in_B $end
$var wire 1 c Data_out_Carry $end
$var wire 1 b Data_out_Sum $end
$upscope $end
$upscope $end
$scope module fa24 $end
$var wire 1 I Data_in_A $end
$var wire 1 8 Data_in_C $end
$var wire 1 D Data_out_Carry $end
$var wire 1 4 Data_out_Sum $end
$var wire 1 f ha2_sum $end
$var wire 1 g ha2_carry $end
$var wire 1 h ha1_sum $end
$var wire 1 i ha1_carry $end
$var wire 1 A Data_in_B $end
$scope module ha1 $end
$var wire 1 I Data_in_A $end
$var wire 1 i Data_out_Carry $end
$var wire 1 h Data_out_Sum $end
$var wire 1 A Data_in_B $end
$upscope $end
$scope module ha2 $end
$var wire 1 8 Data_in_A $end
$var wire 1 h Data_in_B $end
$var wire 1 g Data_out_Carry $end
$var wire 1 f Data_out_Sum $end
$upscope $end
$upscope $end
$scope module fa25 $end
$var wire 1 H Data_in_A $end
$var wire 1 D Data_in_B $end
$var wire 1 C Data_out_Carry $end
$var wire 1 3 Data_out_Sum $end
$var wire 1 j ha2_sum $end
$var wire 1 k ha2_carry $end
$var wire 1 l ha1_sum $end
$var wire 1 m ha1_carry $end
$var wire 1 7 Data_in_C $end
$scope module ha1 $end
$var wire 1 H Data_in_A $end
$var wire 1 D Data_in_B $end
$var wire 1 m Data_out_Carry $end
$var wire 1 l Data_out_Sum $end
$upscope $end
$scope module ha2 $end
$var wire 1 l Data_in_B $end
$var wire 1 k Data_out_Carry $end
$var wire 1 j Data_out_Sum $end
$var wire 1 7 Data_in_A $end
$upscope $end
$upscope $end
$scope module fa26 $end
$var wire 1 C Data_in_B $end
$var wire 1 n Data_in_C $end
$var wire 1 B Data_out_Carry $end
$var wire 1 2 Data_out_Sum $end
$var wire 1 o ha2_sum $end
$var wire 1 p ha2_carry $end
$var wire 1 q ha1_sum $end
$var wire 1 r ha1_carry $end
$var wire 1 G Data_in_A $end
$scope module ha1 $end
$var wire 1 C Data_in_B $end
$var wire 1 r Data_out_Carry $end
$var wire 1 q Data_out_Sum $end
$var wire 1 G Data_in_A $end
$upscope $end
$scope module ha2 $end
$var wire 1 n Data_in_A $end
$var wire 1 q Data_in_B $end
$var wire 1 p Data_out_Carry $end
$var wire 1 o Data_out_Sum $end
$upscope $end
$upscope $end
$scope module ha11 $end
$var wire 1 s Data_in_A $end
$var wire 1 t Data_in_B $end
$var wire 1 K Data_out_Carry $end
$var wire 1 ; Data_out_Sum $end
$upscope $end
$scope module ha15 $end
$var wire 1 u Data_in_A $end
$var wire 1 v Data_in_B $end
$var wire 1 G Data_out_Carry $end
$var wire 1 7 Data_out_Sum $end
$upscope $end
$scope module ha22 $end
$var wire 1 K Data_in_A $end
$var wire 1 : Data_in_B $end
$var wire 1 F Data_out_Carry $end
$var wire 1 6 Data_out_Sum $end
$upscope $end
$scope module ha32 $end
$var wire 1 F Data_in_A $end
$var wire 1 5 Data_in_B $end
$var wire 1 A Data_out_Carry $end
$var wire 1 1 Data_out_Sum $end
$upscope $end
$scope module ha34 $end
$var wire 1 E Data_in_A $end
$var wire 1 4 Data_in_B $end
$var wire 1 @ Data_out_Carry $end
$var wire 1 0 Data_out_Sum $end
$upscope $end
$scope module ha35 $end
$var wire 1 @ Data_in_A $end
$var wire 1 3 Data_in_B $end
$var wire 1 ? Data_out_Carry $end
$var wire 1 / Data_out_Sum $end
$upscope $end
$scope module ha36 $end
$var wire 1 ? Data_in_A $end
$var wire 1 2 Data_in_B $end
$var wire 1 > Data_out_Carry $end
$var wire 1 . Data_out_Sum $end
$upscope $end
$scope module ha37 $end
$var wire 1 > Data_in_A $end
$var wire 1 B Data_in_B $end
$var wire 1 = Data_out_Carry $end
$var wire 1 - Data_out_Sum $end
$upscope $end
$upscope $end
$upscope $end
$enddefinitions $end
$comment Show the parameter values. $end
$dumpall
$end
#0
$dumpvars
0v
0u
0t
0s
0r
0q
0p
0o
0n
0m
0l
0k
0j
0i
0h
0g
0f
0e
0d
0c
0b
0a
0`
0_
0^
0]
0\
0[
0Z
0Y
0X
0W
0V
0U
0T
0S
0R
0Q
0P
0O
0N
0M
0L
0K
0J
0I
0H
0G
0F
0E
0D
0C
0B
0A
0@
0?
0>
0=
b0 <
0;
0:
09
08
07
06
05
04
03
02
01
00
0/
0.
0-
b0 ,
b0 +
b0 *
b0 )
b0 (
b0 '
b0 &
b0 %
b0 $
b0 #
b0 "
b0 !
$end
#1
b1 #
b1 (
b1 &
#2
b10 #
b10 (
b10 &
#3
b11 #
b11 (
b11 &
#4
b100 #
b100 (
b100 &
#5
b101 #
b101 (
b101 &
#6
b110 #
b110 (
b110 &
#7
b111 #
b111 (
b111 &
#8
b1000 #
b1000 (
b1000 &
#9
b1001 #
b1001 (
b1001 &
#10
b1010 #
b1010 (
b1010 &
#11
b1011 #
b1011 (
b1011 &
#12
b1100 #
b1100 (
b1100 &
#13
b1101 #
b1101 (
b1101 &
#14
b1110 #
b1110 (
b1110 &
#15
b1111 #
b1111 (
b1111 &
#16
01
06
05
0b
0;
0:
0O
0d
b0 !
b0 <
0t
0N
0a
b0 )
b0 *
b0 +
b0 ,
b0 #
b0 (
b1 "
b1 '
b1 %
b0 &
#17
b1 !
b1 <
b1 )
b1 #
b1 (
b1 &
#18
1;
b10 !
b10 <
1t
b0 )
b1 *
b10 #
b10 (
b10 &
#19
b11 !
b11 <
b1 )
b11 #
b11 (
b11 &
#20
16
0;
1:
1O
b100 !
b100 <
0t
1N
b0 )
b0 *
b1 +
b100 #
b100 (
b100 &
#21
b101 !
b101 <
b1 )
b101 #
b101 (
b101 &
#22
1;
b110 !
b110 <
1t
b0 )
b1 *
b110 #
b110 (
b110 &
#23
b111 !
b111 <
b1 )
b111 #
b111 (
b111 &
#24
11
06
15
1b
0;
0:
0O
1d
b1000 !
b1000 <
0t
0N
1a
b0 )
b0 *
b0 +
b1 ,
b1000 #
b1000 (
b1000 &
#25
b1001 !
b1001 <
b1 )
b1001 #
b1001 (
b1001 &
#26
1;
b1010 !
b1010 <
1t
b0 )
b1 *
b1010 #
b1010 (
b1010 &
#27
b1011 !
b1011 <
b1 )
b1011 #
b1011 (
b1011 &
#28
16
0;
1:
1O
b1100 !
b1100 <
0t
1N
b0 )
b0 *
b1 +
b1100 #
b1100 (
b1100 &
#29
b1101 !
b1101 <
b1 )
b1101 #
b1101 (
b1101 &
#30
1;
b1110 !
b1110 <
1t
b0 )
b1 *
b1110 #
b1110 (
b1110 &
#31
b1111 !
b1111 <
b1 )
b1111 #
b1111 (
b1111 &
#32
01
05
0b
00
0;
06
04
0f
0Q
0:
0O
09
0V
08
0]
0d
b0 !
b0 <
0s
0t
0M
0N
0U
0\
0a
b0 )
b0 *
b0 +
b0 ,
b0 #
b0 (
b10 "
b10 '
b10 %
b0 &
#33
b10 !
b10 <
1;
1s
b10 )
b1 #
b1 (
b1 &
#34
16
1:
1O
b100 !
b100 <
0;
1Q
0s
1M
b0 )
b10 *
b10 #
b10 (
b10 &
#35
b110 !
b110 <
1;
1s
b10 )
b11 #
b11 (
b11 &
#36
06
11
0:
0O
15
1b
b1000 !
b1000 <
0;
0Q
19
1V
0s
0M
1U
b0 )
b0 *
b10 +
b100 #
b100 (
b100 &
#37
b1010 !
b1010 <
1;
1s
b10 )
b101 #
b101 (
b101 &
#38
16
1:
1O
b1100 !
b1100 <
0;
1Q
0s
1M
b0 )
b10 *
b110 #
b110 (
b110 &
#39
b1110 !
b1110 <
1;
1s
b10 )
b111 #
b111 (
b111 &
#40
06
01
10
0:
0O
05
0b
14
1f
b10000 !
b10000 <
0;
0Q
09
0V
18
1]
0s
0M
0U
1\
b0 )
b0 *
b0 +
b10 ,
b1000 #
b1000 (
b1000 &
#41
b10010 !
b10010 <
1;
1s
b10 )
b1001 #
b1001 (
b1001 &
#42
16
1:
1O
b10100 !
b10100 <
0;
1Q
0s
1M
b0 )
b10 *
b1010 #
b1010 (
b1010 &
#43
b10110 !
b10110 <
1;
1s
b10 )
b1011 #
b1011 (
b1011 &
#44
06
11
0:
0O
15
1b
b11000 !
b11000 <
0;
0Q
19
1V
0s
0M
1U
b0 )
b0 *
b10 +
b1100 #
b1100 (
b1100 &
#45
b11010 !
b11010 <
1;
1s
b10 )
b1101 #
b1101 (
b1101 &
#46
16
1:
1O
b11100 !
b11100 <
0;
1Q
0s
1M
b0 )
b10 *
b1110 #
b1110 (
b1110 &
#47
b11110 !
b11110 <
1;
1s
b10 )
b1111 #
b1111 (
b1111 &
#48
00
06
04
0f
01
0E
0Q
09
0V
08
0]
0J
05
0b
0c
0s
0M
0U
0\
0;
0K
0:
0O
0P
0d
b0 !
b0 <
0t
0N
0a
b0 )
b0 *
b0 +
b0 ,
b0 #
b0 (
b11 "
b11 '
b11 %
b0 &
#49
1;
b11 !
b11 <
1s
b11 )
b1 #
b1 (
b1 &
#50
16
1:
1O
1Q
b110 !
b110 <
0s
1t
1M
b0 )
b11 *
b10 #
b10 (
b10 &
#51
11
06
1F
0;
1K
b1001 !
b1001 <
1s
b11 )
b11 #
b11 (
b11 &
#52
00
11
0E
0c
16
0d
0F
0J
15
1b
0K
0Q
1:
1O
0P
19
1V
b1100 !
b1100 <
0s
0t
0M
1N
1U
b0 )
b0 *
b11 +
b100 #
b100 (
b100 &
#53
1;
b1111 !
b1111 <
1s
b11 )
b101 #
b101 (
b101 &
#54
10
01
1E
05
0b
1c
1d
06
1J
0:
0O
1P
1Q
b10010 !
b10010 <
0s
1t
1M
b0 )
b11 *
b110 #
b110 (
b110 &
#55
16
0;
1K
b10101 !
b10101 <
1s
b11 )
b111 #
b111 (
b111 &
#56
11
15
1b
0E
0/
06
10
0@
0J
14
1f
0c
0K
0Q
0:
0O
0P
09
0V
18
1]
1d
0e
b11000 !
b11000 <
0s
0t
0M
0N
0U
1\
1a
b0 )
b0 *
b0 +
b11 ,
b1000 #
b1000 (
b1000 &
#57
1;
b11011 !
b11011 <
1s
b11 )
b1001 #
b1001 (
b1001 &
#58
16
1:
1O
1Q
b11110 !
b11110 <
0s
1t
1M
b0 )
b11 *
b1010 #
b1010 (
b1010 &
#59
1/
13
1j
1l
00
1D
04
0f
1g
1h
01
1A
06
1F
0;
1K
b100001 !
b100001 <
1s
b11 )
b1011 #
b1011 (
b1011 &
#60
03
0j
1@
0l
0D
01
14
1f
0g
0h
00
16
1d
0e
0A
1E
0F
0J
05
0b
1c
0K
0Q
1:
1O
0P
19
1V
b100100 !
b100100 <
0s
0t
0M
1N
1U
b0 )
b0 *
b11 +
b1100 #
b1100 (
b1100 &
#61
1;
b100111 !
b100111 <
1s
b11 )
b1101 #
b1101 (
b1101 &
#62
11
15
1b
0c
0d
1e
06
1J
0:
0O
1P
1Q
b101010 !
b101010 <
0s
1t
1M
b0 )
b11 *
b1110 #
b1110 (
b1110 &
#63
16
0;
1K
b101101 !
b101101 <
1s
b11 )
b1111 #
b1111 (
b1111 &
#64
01
06
05
0b
0/
00
0@
0Q
0J
04
0f
03
0j
0E
0K
0X
0:
0O
0P
09
0V
0_
08
0]
07
0d
0e
b0 !
b0 <
0s
0L
0t
0M
0T
0N
0U
0[
0\
0v
0a
b0 )
b0 *
b0 +
b0 ,
b0 #
b0 (
b100 "
b100 '
b100 %
b0 &
#65
b100 !
b100 <
16
1:
1O
1Q
1L
b100 )
b1 #
b1 (
b1 &
#66
11
b1000 !
b1000 <
06
15
1b
0:
0O
19
1V
0Q
1X
0L
1T
b0 )
b100 *
b10 #
b10 (
b10 &
#67
b1100 !
b1100 <
16
1:
1O
1Q
1L
b100 )
b11 #
b11 (
b11 &
#68
01
10
b10000 !
b10000 <
06
05
0b
14
1f
0:
0O
09
0V
18
1]
0Q
0X
1_
0L
0T
1[
b0 )
b0 *
b100 +
b100 #
b100 (
b100 &
#69
b10100 !
b10100 <
16
1:
1O
1Q
1L
b100 )
b101 #
b101 (
b101 &
#70
11
b11000 !
b11000 <
06
15
1b
0:
0O
19
1V
0Q
1X
0L
1T
b0 )
b100 *
b110 #
b110 (
b110 &
#71
b11100 !
b11100 <
16
1:
1O
1Q
1L
b100 )
b111 #
b111 (
b111 &
#72
01
00
06
05
0b
04
0f
b100000 !
b100000 <
1/
0:
0O
09
0V
08
0]
13
1j
0Q
0X
0_
17
0L
0T
0[
1v
b0 )
b0 *
b0 +
b100 ,
b1000 #
b1000 (
b1000 &
#73
b100100 !
b100100 <
16
1:
1O
1Q
1L
b100 )
b1001 #
b1001 (
b1001 &
#74
11
b101000 !
b101000 <
06
15
1b
0:
0O
19
1V
0Q
1X
0L
1T
b0 )
b100 *
b1010 #
b1010 (
b1010 &
#75
b101100 !
b101100 <
16
1:
1O
1Q
1L
b100 )
b1011 #
b1011 (
b1011 &
#76
01
10
b110000 !
b110000 <
06
05
0b
14
1f
0:
0O
09
0V
18
1]
0Q
0X
1_
0L
0T
1[
b0 )
b0 *
b100 +
b1100 #
b1100 (
b1100 &
#77
b110100 !
b110100 <
16
1:
1O
1Q
1L
b100 )
b1101 #
b1101 (
b1101 &
#78
11
b111000 !
b111000 <
06
15
1b
0:
0O
19
1V
0Q
1X
0L
1T
b0 )
b100 *
b1110 #
b1110 (
b1110 &
#79
b111100 !
b111100 <
16
1:
1O
1Q
1L
b100 )
b1111 #
b1111 (
b1111 &
#80
0/
04
0f
00
0@
09
0V
08
0]
03
0j
01
0E
0Q
0X
0_
07
06
0J
05
0b
0c
0L
0T
0[
0v
0;
0:
0O
0P
0d
b0 !
b0 <
0t
0N
0a
b0 )
b0 *
b0 +
b0 ,
b0 #
b0 (
b101 "
b101 '
b101 %
b0 &
#81
16
1:
1O
1Q
b101 !
b101 <
1L
b101 )
b1 #
b1 (
b1 &
#82
11
06
15
1b
0:
0O
19
1V
0Q
1;
1X
b1010 !
b1010 <
0L
1t
1T
b0 )
b101 *
b10 #
b10 (
b10 &
#83
16
1:
1O
1Q
b1111 !
b1111 <
1L
b101 )
b11 #
b11 (
b11 &
#84
01
05
0b
10
0d
14
1f
09
0V
16
0J
18
1]
0Q
0;
0X
1:
1O
0P
1_
b10100 !
b10100 <
0L
0t
0T
1N
1[
b0 )
b0 *
b101 +
b100 #
b100 (
b100 &
#85
11
15
1b
1d
06
1J
0:
0O
1P
1Q
b11001 !
b11001 <
1L
b101 )
b101 #
b101 (
b101 &
#86
0/
10
0@
0d
11
0E
16
0J
15
1b
0c
1:
1O
0P
19
1V
0Q
1;
1X
b11110 !
b11110 <
0L
1t
1T
b0 )
b101 *
b110 #
b110 (
b110 &
#87
1/
00
1@
01
1E
05
0b
1c
1d
06
1J
0:
0O
1P
1Q
b100011 !
b100011 <
1L
b101 )
b111 #
b111 (
b111 &
#88
0E
00
0@
0.
04
0f
1/
0?
11
09
0V
06
0J
08
0]
13
1j
15
1b
0c
0Q
0;
0X
0:
0O
0P
0_
17
1d
0e
b101000 !
b101000 <
0L
0t
0T
0N
0[
1v
1a
b0 )
b0 *
b0 +
b101 ,
b1000 #
b1000 (
b1000 &
#89
16
1:
1O
1Q
b101101 !
b101101 <
1L
b101 )
b1001 #
b1001 (
b1001 &
#90
10
01
1E
06
05
0b
1c
0:
0O
19
1V
0Q
1;
1X
b110010 !
b110010 <
0L
1t
1T
b0 )
b101 *
b1010 #
b1010 (
b1010 &
#91
16
1:
1O
1Q
b110111 !
b110111 <
1L
b101 )
b1011 #
b1011 (
b1011 &
#92
11
0.
15
1b
0E
1/
0?
10
0@
0c
1d
0e
14
1f
09
0V
16
0J
18
1]
0Q
0;
0X
1:
1O
0P
1_
b111100 !
b111100 <
0L
0t
0T
1N
1[
b0 )
b0 *
b101 +
b1100 #
b1100 (
b1100 &
#93
1.
0/
1?
01
00
1@
05
0b
1E
0d
1e
06
1J
0:
0O
1P
1Q
b1000001 !
b1000001 <
1L
b101 )
b1101 #
b1101 (
b1101 &
#94
1.
0/
1?
00
1@
1c
1E
1d
0e
01
16
0J
05
0b
1:
1O
0P
19
1V
0Q
1;
1X
b1000110 !
b1000110 <
0L
1t
1T
b0 )
b101 *
b1110 #
b1110 (
b1110 &
#95
11
15
1b
0c
0d
1e
06
1J
0:
0O
1P
1Q
b1001011 !
b1001011 <
1L
b101 )
b1111 #
b1111 (
b1111 &
#96
03
0j
0.
01
0D
0/
0?
0J
05
0b
0c
0g
0h
0l
0@
0;
0X
0_
07
06
0I
04
0f
0H
0E
0L
0T
0[
0v
0Q
0R
0:
0O
0P
09
0V
0W
08
0]
0^
0d
0e
b0 !
b0 <
0s
0t
0M
0N
0U
0\
0a
b0 )
b0 *
b0 +
b0 ,
b0 #
b0 (
b110 "
b110 '
b110 %
b0 &
#97
16
1:
1O
b110 !
b110 <
1;
1Q
1s
1L
b110 )
b1 #
b1 (
b1 &
#98
11
15
1b
19
1V
b1100 !
b1100 <
0;
1X
0s
0L
1M
1T
b0 )
b110 *
b10 #
b10 (
b10 &
#99
10
01
1E
05
0b
1c
06
1d
0:
0O
1J
b10010 !
b10010 <
1;
0Q
1R
1s
1L
b110 )
b11 #
b11 (
b11 &
#100
0/
03
0j
0l
0D
0g
0d
11
0E
0h
14
1f
0J
15
1b
0c
0I
18
1]
b11000 !
b11000 <
0;
0R
0X
19
1V
0W
1_
0s
0L
0M
0T
1U
1[
b0 )
b0 *
b110 +
b100 #
b100 (
b100 &
#101
16
1:
1O
b11110 !
b11110 <
1;
1Q
1s
1L
b110 )
b101 #
b101 (
b101 &
#102
1/
13
1j
1l
00
1D
04
0f
1g
01
1h
05
0b
1I
09
0V
1W
b100100 !
b100100 <
0;
1X
0s
0L
1M
1T
b0 )
b110 *
b110 #
b110 (
b110 &
#103
11
15
1b
06
1d
0:
0O
1J
b101010 !
b101010 <
1;
0Q
1R
1s
1L
b110 )
b111 #
b111 (
b111 &
#104
0.
02
0o
0q
0d
01
0E
0h
10
0D
0l
0m
0C
1/
0J
05
0b
0c
0I
14
1f
0g
0H
0k
13
1j
b110000 !
b110000 <
0;
0R
0X
09
0V
0W
0_
18
1]
0^
17
0s
0L
0M
0T
0U
0[
1\
1v
b0 )
b0 *
b0 +
b110 ,
b1000 #
b1000 (
b1000 &
#105
16
1:
1O
b110110 !
b110110 <
1;
1Q
1s
1L
b110 )
b1001 #
b1001 (
b1001 &
#106
11
15
1b
19
1V
b111100 !
b111100 <
0;
1X
0s
0L
1M
1T
b0 )
b110 *
b1010 #
b1010 (
b1010 &
#107
1.
0/
1?
00
1@
01
1E
05
0b
1c
06
1d
0:
0O
1J
b1000010 !
b1000010 <
1;
0Q
1R
1s
1L
b110 )
b1011 #
b1011 (
b1011 &
#108
12
1o
1q
0/
1.
1C
0?
03
0j
1k
0@
1l
0d
11
0E
0h
04
0f
1H
0J
15
1b
0c
0I
08
0]
1^
b1001000 !
b1001000 <
0;
0R
0X
19
1V
0W
1_
0s
0L
0M
0T
1U
1[
b0 )
b0 *
b110 +
b1100 #
b1100 (
b1100 &
#109
16
1:
1O
b1001110 !
b1001110 <
1;
1Q
1s
1L
b110 )
b1101 #
b1101 (
b1101 &
#110
10
14
1f
01
1h
05
0b
1I
09
0V
1W
b1010100 !
b1010100 <
0;
1X
0s
0L
1M
1T
b0 )
b110 *
b1110 #
b1110 (
b1110 &
#111
11
15
1b
06
1d
0:
0O
1J
b1011010 !
b1011010 <
1;
0Q
1R
1s
1L
b110 )
b1111 #
b1111 (
b1111 &
#112
02
0o
0-
0q
0/
0.
0>
01
0h
0D
0l
0C
0?
0J
0I
04
0f
0g
0H
0k
03
0j
0c
00
0@
0R
0X
09
0V
0W
0_
08
0]
0^
07
0F
05
0b
0E
0s
0L
0M
0T
0U
0[
0\
0v
0;
0K
0:
0O
0d
0e
b0 !
b0 <
0t
0N
0a
b0 )
b0 *
b0 +
b0 ,
b0 #
b0 (
b111 "
b111 '
b111 %
b0 &
#113
16
1:
1O
1;
1Q
b111 !
b111 <
1s
1L
b111 )
b1 #
b1 (
b1 &
#114
11
15
1b
19
1V
1X
b1110 !
b1110 <
0s
0L
1t
1M
1T
b0 )
b111 *
b10 #
b10 (
b10 &
#115
10
01
1E
05
0b
1c
1d
0:
0O
1J
0;
1K
0Q
1R
b10101 !
b10101 <
1s
1L
b111 )
b11 #
b11 (
b11 &
#116
0/
03
0j
0l
0D
0g
0d
11
0E
0h
14
1f
0J
15
1b
0c
0I
18
1]
0K
0R
0X
1:
1O
19
1V
0W
1_
b11100 !
b11100 <
0s
0L
0t
0M
0T
1N
1U
1[
b0 )
b0 *
b111 +
b100 #
b100 (
b100 &
#117
1/
00
1@
01
1E
05
0b
1c
1d
06
1J
0:
0O
1P
1;
1Q
b100011 !
b100011 <
1s
1L
b111 )
b101 #
b101 (
b101 &
#118
13
1j
1l
1/
1D
0@
04
0f
1g
11
0E
1h
15
1b
0c
1I
09
0V
1W
1X
b101010 !
b101010 <
0s
0L
1t
1M
1T
b0 )
b111 *
b110 #
b110 (
b110 &
#119
10
14
1f
0g
1i
0h
01
1A
1F
1:
1O
0P
0;
1K
0Q
1R
b110001 !
b110001 <
1s
1L
b111 )
b111 #
b111 (
b111 &
#120
0.
0-
0>
0?
02
0o
0g
0D
10
0@
0q
15
1b
11
0A
0h
0i
0l
0m
0C
1/
0J
0F
0I
14
1f
0H
0k
13
1j
0E
0K
0R
0X
0:
0O
09
0V
0W
0_
18
1]
0^
17
1d
0e
b111000 !
b111000 <
0s
0L
0t
0M
0T
0N
0U
0[
1\
1v
1a
b0 )
b0 *
b0 +
b111 ,
b1000 #
b1000 (
b1000 &
#121
16
1:
1O
1;
1Q
b111111 !
b111111 <
1s
1L
b111 )
b1001 #
b1001 (
b1001 &
#122
1.
0/
1?
00
1@
01
1E
05
0b
1c
19
1V
1X
b1000110 !
b1000110 <
0s
0L
1t
1M
1T
b0 )
b111 *
b1010 #
b1010 (
b1010 &
#123
11
15
1b
0c
0d
1e
0:
0O
1J
0;
1K
0Q
1R
b1001101 !
b1001101 <
1s
1L
b111 )
b1011 #
b1011 (
b1011 &
